gemini_list_mapper/__init__.py
gemini_list_mapper/config.template.yml
gemini_list_mapper/mapper.py
gemini_list_mapper-0.1.0.dist-info/METADATA
gemini_list_mapper-0.1.0.dist-info/WHEEL
gemini_list_mapper-0.1.0.dist-info/top_level.txt
gemini_list_mapper-0.1.0.dist-info/RECORD
