Metadata-Version: 2.4
Name: gemini-list-mapper
Version: 0.1.0
Summary: A robust list-to-list mapping utility powered by Google Gemini, ensuring output size consistency for any user-defined task.
Author-email: zhanngpenng <zhanngpenng@gmail.com>
License: MIT License
Keywords: gemini,ai,llm,list processing,mapper,translation
Classifier: Development Status :: 4 - Beta
Classifier: Intended Audience :: Developers
Classifier: License :: OSI Approved :: MIT License
Classifier: Operating System :: OS Independent
Classifier: Programming Language :: Python :: 3
Classifier: Programming Language :: Python :: 3.8
Classifier: Programming Language :: Python :: 3.9
Classifier: Programming Language :: Python :: 3.10
Classifier: Programming Language :: Python :: 3.11
Classifier: Topic :: Text Processing :: Linguistic
Classifier: Topic :: Software Development :: Libraries :: Python Modules
Requires-Python: >=3.9.21
Requires-Dist: google-generativeai>=0.8.5
Requires-Dist: PyYAML>=6.0
Requires-Dist: numpy>=1.20
Requires-Dist: tqdm>=4.0
Requires-Dist: colorama>=0.4
